traveltime_drive_time_comparisons/__init__.py
traveltime_drive_time_comparisons/analysis.py
traveltime_drive_time_comparisons/case_analysis.py
traveltime_drive_time_comparisons/collect.py
traveltime_drive_time_comparisons/common.py
traveltime_drive_time_comparisons/config.py
traveltime_drive_time_comparisons/main.py
traveltime_drive_time_comparisons/plot.py
traveltime_drive_time_comparisons/api_requests/__init__.py
traveltime_drive_time_comparisons/api_requests/base_handler.py
traveltime_drive_time_comparisons/api_requests/factory.py
traveltime_drive_time_comparisons/api_requests/google_handler.py
traveltime_drive_time_comparisons/api_requests/google_handler_new.py
traveltime_drive_time_comparisons/api_requests/here_handler.py
traveltime_drive_time_comparisons/api_requests/mapbox_handler.py
traveltime_drive_time_comparisons/api_requests/tomtom_handler.py
traveltime_drive_time_comparisons/api_requests/traveltime_credentials.py
traveltime_drive_time_comparisons/api_requests/traveltime_handler.py
traveltime_drive_time_comparisons-1.6.3.dist-info/licenses/LICENSE
traveltime_drive_time_comparisons-1.6.3.dist-info/METADATA
traveltime_drive_time_comparisons-1.6.3.dist-info/WHEEL
traveltime_drive_time_comparisons-1.6.3.dist-info/entry_points.txt
traveltime_drive_time_comparisons-1.6.3.dist-info/top_level.txt
traveltime_drive_time_comparisons-1.6.3.dist-info/RECORD
