Metadata-Version: 2.4
Name: traveltime-drive-time-comparisons
Version: 1.6.3
Summary: Compare travel times obtained from TravelTime API other API providers
Author: TravelTime
Project-URL: Homepage, https://github.com/traveltime-dev/traveltime-drive-time-comparisons
Classifier: Programming Language :: Python :: 3
Classifier: Programming Language :: Python :: 3.9
Classifier: Programming Language :: Python :: 3.10
Classifier: Programming Language :: Python :: 3.11
Classifier: Programming Language :: Python :: 3.12
Classifier: Programming Language :: Python :: 3.13
Classifier: License :: OSI Approved :: MIT License
Requires-Python: >=3.9
License-File: LICENSE
Requires-Dist: aiohttp
Requires-Dist: aiolimiter
Requires-Dist: pandas
Requires-Dist: numpy
Requires-Dist: pytz
Requires-Dist: PyQt5
Requires-Dist: matplotlib
Requires-Dist: traveltimepy>=4.0.0
Provides-Extra: test
Requires-Dist: pytest; extra == "test"
Requires-Dist: flake8; extra == "test"
Requires-Dist: flake8-pyproject; extra == "test"
Requires-Dist: mypy; extra == "test"
Requires-Dist: black; extra == "test"
Dynamic: license-file
